{
  "Agreement Rate": {},
  "N. Optimality": {},
  "P. Optimality": {},
  "Rounds": {
    "TAU$(\\infty, 0)$+SCS-AOP($2 n_o$)+Atlas3": [
      1.0,
      1.52587890625e-05
    ],
    "TAU$(\\infty, 0)$+SCS-AOP(3min)+Atlas3": [
      1.0,
      1.52587890625e-05
    ],
    "TAU$(\\infty, \\infty)$+SCS-AOP($2 n_o$)+Atlas3": [
      1.0,
      1.52587890625e-05
    ],
    "TAU$(\\infty, \\infty)$+SCS-AOP(3min)+Atlas3": [
      1.0,
      1.52587890625e-05
    ]
  },
  "Time": {
    "TAU$(\\infty, 0)$+SCS-AOP($2 n_o$)+Atlas3": [
      1.0,
      1.52587890625e-05
    ],
    "TAU$(\\infty, 0)$+SCS-AOP(3min)+Atlas3": [
      0.0,
      7.62939453125e-06
    ],
    "TAU$(\\infty, \\infty)$+SCS-AOP($2 n_o$)+Atlas3": [
      0.0,
      7.62939453125e-06
    ],
    "TAU$(\\infty, \\infty)$+SCS-AOP(3min)+Atlas3": [
      0.0,
      7.62939453125e-06
    ]
  },
  "Utility": {},
  "Welfare": {}
}